suru/__init__.py
suru-0.3.4.dist-info/METADATA
suru-0.3.4.dist-info/WHEEL
suru-0.3.4.dist-info/entry_points.txt
suru-0.3.4.dist-info/RECORD
