Metadata-Version: 2.3
Name: suru
Version: 0.3.4
Summary: Add your description here
Author-email: Jianqi Pan <jannchie@gmail.com>
Requires-Python: >=3.8
Requires-Dist: dynaconf>=3.2.6
Requires-Dist: inquirer>=3.4.0
Requires-Dist: openai>=1.42.0
Requires-Dist: rich>=13.7.1
